pymetacode/__init__.py
pymetacode/cli.py
pymetacode/coding.py
pymetacode/configuration.py
pymetacode/utils.py
pymetacode/__pycache__/__init__.cpython-311.pyc
pymetacode/__pycache__/__init__.cpython-39.pyc
pymetacode/__pycache__/cli.cpython-311.pyc
pymetacode/__pycache__/cli.cpython-39.pyc
pymetacode/__pycache__/coding.cpython-311.pyc
pymetacode/__pycache__/coding.cpython-39.pyc
pymetacode/__pycache__/configuration.cpython-311.pyc
pymetacode/__pycache__/configuration.cpython-39.pyc
pymetacode/__pycache__/utils.cpython-311.pyc
pymetacode/__pycache__/utils.cpython-39.pyc
pymetacode/templates/CITATION.j2.cff
pymetacode/templates/MANIFEST-gui.j2.in
pymetacode/templates/MANIFEST.j2.in
pymetacode/templates/Makefile
pymetacode/templates/Makefile_gui
pymetacode/templates/README.j2.rst
pymetacode/templates/formatPythonCode.sh
pymetacode/templates/gitignore
pymetacode/templates/icon.svg
pymetacode/templates/incrementVersion.sh
pymetacode/templates/prospector.j2.yaml
pymetacode/templates/pyproject.j2.toml
pymetacode/templates/setup-gui-scripts.j2.py
pymetacode/templates/setup.j2.py
pymetacode/templates/splash.j2.svg
pymetacode/templates/code/class.j2.py
pymetacode/templates/code/function.j2.py
pymetacode/templates/code/gui_app.j2.py
pymetacode/templates/code/gui_dialog.j2.py
pymetacode/templates/code/gui_mainwindow.j2.py
pymetacode/templates/code/gui_widget.j2.py
pymetacode/templates/code/gui_window.j2.py
pymetacode/templates/code/gui_window.j2.ui
pymetacode/templates/code/module.j2.py
pymetacode/templates/code/test_class.j2.py
pymetacode/templates/code/test_function.j2.py
pymetacode/templates/code/test_guiclass.j2.py
pymetacode/templates/code/test_guimodule.j2.py
pymetacode/templates/code/test_module.j2.py
pymetacode/templates/docs/Makefile
pymetacode/templates/docs/api_gui_module.j2.rst
pymetacode/templates/docs/api_index.j2.rst
pymetacode/templates/docs/api_index_subpackages_block.j2.rst
pymetacode/templates/docs/api_module.j2.rst
pymetacode-0.7.0.dist-info/licenses/LICENSE
pymetacode-0.7.0.dist-info/METADATA
pymetacode-0.7.0.dist-info/WHEEL
pymetacode-0.7.0.dist-info/entry_points.txt
pymetacode-0.7.0.dist-info/top_level.txt
pymetacode-0.7.0.dist-info/RECORD
