Metadata-Version: 2.4
Name: pymetacode
Version: 0.7.0
Summary: A Python package helping to write and maintain Python packages.
Home-page: https://www.meta-co.de/
Author: Till Biskup
Author-email: till@till-biskup.de
License: BSD
Project-URL: Documentation, https://python.docs.meta-co.de/
Project-URL: Source, https://github.com/tillbiskup/pymetacode
Keywords: metaprogramming,Python packages,automation,code generation
Classifier: Programming Language :: Python :: 3
Classifier: Programming Language :: Python :: 3.7
Classifier: Programming Language :: Python :: 3.8
Classifier: Programming Language :: Python :: 3.9
Classifier: Programming Language :: Python :: 3.10
Classifier: Programming Language :: Python :: 3.11
Classifier: Programming Language :: Python :: 3.12
Classifier: License :: OSI Approved :: BSD License
Classifier: Operating System :: OS Independent
Classifier: Environment :: Console
Classifier: Intended Audience :: Developers
Classifier: Intended Audience :: Science/Research
Classifier: Topic :: Software Development
Classifier: Topic :: Software Development :: Code Generators
Classifier: Development Status :: 5 - Production/Stable
Requires-Python: >=3.7
License-File: LICENSE
Requires-Dist: jinja2
Requires-Dist: pyyaml
Requires-Dist: platformdirs
Provides-Extra: dev
Requires-Dist: prospector; extra == "dev"
Requires-Dist: pyroma; extra == "dev"
Requires-Dist: bandit; extra == "dev"
Requires-Dist: black; extra == "dev"
Provides-Extra: docs
Requires-Dist: sphinx; extra == "docs"
Requires-Dist: sphinx-rtd-theme; extra == "docs"
Requires-Dist: sphinx-multiversion; extra == "docs"
Provides-Extra: deployment
Requires-Dist: build; extra == "deployment"
Requires-Dist: twine; extra == "deployment"
Dynamic: author
Dynamic: author-email
Dynamic: classifier
Dynamic: description
Dynamic: description-content-type
Dynamic: home-page
Dynamic: keywords
Dynamic: license
Dynamic: license-file
Dynamic: project-url
Dynamic: provides-extra
Dynamic: requires-dist
Dynamic: requires-python
Dynamic: summary
